MANIFEST.in
README.md
setup.cfg
setup.py
rent_a_bot.egg-info/PKG-INFO
rent_a_bot.egg-info/SOURCES.txt
rent_a_bot.egg-info/dependency_links.txt
rent_a_bot.egg-info/requires.txt
rent_a_bot.egg-info/top_level.txt
rentabot/__init__.py
rentabot/controllers.py
rentabot/exceptions.py
rentabot/logger.py
rentabot/models.py
rentabot/views.py
rentabot/templates/display_resources.html