Metadata-Version: 1.1
Name: rent-a-bot
Version: 0.1.0
Summary: Rent-A-Bot, your automation resource provider.
Home-page: https://github.com/cpoisson/rent-a-bot
Author: Charles Poisson
Author-email: charles.poisson@gmail.com
License: MIT
Keywords: Resource allocation application for automation
Platform: UNKNOWN
Classifier: Framework :: Flask
Classifier: Development Status :: 4 - Beta
Classifier: Intended Audience :: Developers
Classifier: Intended Audience :: System Administrators
Classifier: Topic :: Utilities
Classifier: Operating System :: POSIX :: Linux
Classifier: License :: OSI Approved :: MIT License
Classifier: Programming Language :: Python :: 2.7
Classifier: Programming Language :: Python :: 3.5
Classifier: Programming Language :: Python :: 3.6
